generator/__init__.py
generator/gen.py
android_asset_generator-1.0.6.dist-info/LICENSE
android_asset_generator-1.0.6.dist-info/METADATA
android_asset_generator-1.0.6.dist-info/WHEEL
android_asset_generator-1.0.6.dist-info/entry_points.txt
android_asset_generator-1.0.6.dist-info/top_level.txt
android_asset_generator-1.0.6.dist-info/RECORD
