Metadata-Version: 2.1
Name: android-asset-generator
Version: 1.0.6
Summary: A simple android assets generator
Home-page: https://pypi.org/project/android-asset-generator/
Author: Alejandro Pascual
Author-email: alex_paz_5599@hotmail.com
License: UNKNOWN
Platform: UNKNOWN
Classifier: Programming Language :: Python :: 3
Classifier: License :: OSI Approved :: MIT License
Classifier: Operating System :: OS Independent
Requires-Python: >=3.8
Requires-Dist: python-resize-image
